{
  "statusCode": 0,
  "body": [
    {
      "exploreList": [
        {
          "cardItem": {
            "id": "86328792343818240",
            "type": 2,
            "cover": "https://p16-pu-sign-useast8.tiktokcdn-us.com/tos-useast5-avt-0068-tx/c6325491370d28f7c5f40789e60a79a8~c5_100x100.jpeg?lk3s=a5d48078&nonce=16946&refresh_token=051a12a5eea7f655d7a686cb76743c72&x-expires=1725854400&x-signature=PGDzBnv2o%2F5Xv%2BI0185rK7CcyLU%3D&shp=a5d48078&shcp=b59d6b55",
            "title": "tate mcrae",
            "subTitle": "@tatemcrae",
            "description": "i’m 21. \nIt’s ok I’m ok out september 12. pre-save now",
            "link": "/@tatemcrae",
            "round": true,
            "playToken": "",
            "keyToken": "",
            "extraInfo": {
              "verified": true,
              "fans": 7400000,
              "likes": 325800000,
              "userId": "86328792343818240",
              "secUid": "MS4wLjABAAAA-0bQT0CqebTRr6I4IkYvMDMKSRSJHLNPBo5HrSklJwyA2psXLSZG5FP-LMNpHnJd",
              "relation": 0,
              "video": 949,
              "following": 362,
              "heart": 325800000,
              "digg": 72700
            }
          }
        },
        {
          "cardItem": {
            "id": "7047450743465477126",
            "type": 2,
            "cover": "https://p16-sign.tiktokcdn-us.com/tos-useast5-avt-0068-tx/7310298084372660270~c5_100x100.jpeg?lk3s=a5d48078&nonce=19530&refresh_token=2b1fb1f46080f72814a543dd0c9d0059&x-expires=1725854400&x-signature=d21BOdXRMU8lN%2B68%2F9gqu156Enc%3D&shp=a5d48078&shcp=b59d6b55",
            "title": "Bad Bunny",
            "subTitle": "@badbunny",
            "description": ".",
            "link": "/@badbunny",
            "round": true,
            "playToken": "",
            "keyToken": "",
            "extraInfo": {
              "verified": true,
              "fans": 31100000,
              "likes": 347900000,
              "userId": "7047450743465477126",
              "secUid": "MS4wLjABAAAAhxvSFp8FPW1xhPCzgTzExrCo7Onwd2CuvldSXoUM5oSMLsfR8p6wBNMiWVgBg6V_",
              "relation": 0,
              "video": 0,
              "following": 0,
              "heart": 347900000,
              "digg": 154
            }
          }
        },
        {
          "cardItem": {
            "id": "6745191554350760966",
            "type": 2,
            "cover": "https://p16-sign-va.tiktokcdn.com/tos-maliva-avt-0068/7310325298631802885~c5_100x100.jpeg?lk3s=a5d48078&nonce=70060&refresh_token=f25c10fe38d18d9a9bb9d8302676e715&x-expires=1725854400&x-signature=rcooeOqrte35ybb0NbxdtNySFY4%3D&shp=a5d48078&shcp=b59d6b55",
            "title": "The Rock",
            "subTitle": "@therock",
            "description": "CEO of #RockTok\nLife’s so much sweeter when you’re not an asshole",
            "link": "/@therock",
            "round": true,
            "playToken": "",
            "keyToken": "",
            "extraInfo": {
              "verified": true,
              "fans": 74900000,
              "likes": 558400000,
              "userId": "6745191554350760966",
              "secUid": "MS4wLjABAAAAM3R2BtjzVT-uAtstkl2iugMzC6AtnpkojJbjiOdDDrdsTiTR75-8lyWJCY5VvDrZ",
              "relation": 0,
              "video": 296,
              "following": 0,
              "heart": 558400000,
              "digg": 15
            }
          }
        },
        {
          "cardItem": {
            "id": "6760381874016912390",
            "type": 2,
            "cover": "https://p16-sign-va.tiktokcdn.com/tos-maliva-avt-0068/7310859312619782150~c5_100x100.jpeg?lk3s=a5d48078&nonce=36685&refresh_token=f5557605ad15a5f9c4772c55ebeb8274&x-expires=1725854400&x-signature=T8rDf7o%2BWYyIE27aXEUve8csk8w%3D&shp=a5d48078&shcp=b59d6b55",
            "title": "Olivia Rodrigo",
            "subTitle": "@livbedumb",
            "description": "spicy pisces",
            "link": "/@livbedumb",
            "round": true,
            "playToken": "",
            "keyToken": "",
            "extraInfo": {
              "verified": true,
              "fans": 21800000,
              "likes": 321800000,
              "userId": "6760381874016912390",
              "secUid": "MS4wLjABAAAAnb7UrYm7BoqTzDSu6XphP68sueqPwuXJeHhJcYMye9NNlA7-nh427qHb_e-Al5ES",
              "relation": 0,
              "video": 111,
              "following": 0,
              "heart": 321800000,
              "digg": 5697
            }
          }
        },
        {
          "cardItem": {
            "id": "126223816648822784",
            "type": 2,
            "cover": "https://p19-pu-sign-useast8.tiktokcdn-us.com/tos-useast5-avt-0068-tx/88f48283fb6c9d2744f01249583c89f8~c5_100x100.jpeg?lk3s=a5d48078&nonce=32887&refresh_token=b6ad96845a8f40387cf8264971fa7394&x-expires=1725854400&x-signature=a9gTrkgdAoIwtAnn%2FD02%2F0ssi28%3D&shp=a5d48078&shcp=b59d6b55",
            "title": "rauwalejandro",
            "subTitle": "@rauwalejandro",
            "description": "Latin R&B/Reggaeton singer 🇵🇷",
            "link": "/@rauwalejandro",
            "round": true,
            "playToken": "",
            "keyToken": "",
            "extraInfo": {
              "verified": true,
              "fans": 16100000,
              "likes": 136300000,
              "userId": "126223816648822784",
              "secUid": "MS4wLjABAAAA7pFJYt0Ui6BV6xS9xncL3Zi1NsHEmfdn2t6sMY1yulhbrSWQ29xtwpUQFml62_q0",
              "relation": 0,
              "video": 78,
              "following": 2,
              "heart": 136300000,
              "digg": 179
            }
          }
        },
        {
          "cardItem": {
            "id": "168541398546182144",
            "type": 2,
            "cover": "https://p19-pu-sign-useast8.tiktokcdn-us.com/tos-useast8-avt-0068-tx2/343dc0f14b6ddb106a5fdf86934d3b03~c5_100x100.jpeg?lk3s=a5d48078&nonce=6176&refresh_token=571b80f3031077b8256e3dd8b7c07fc0&x-expires=1725854400&x-signature=3JZETKw8VLg0MxRkkdjres3ciWM%3D&shp=a5d48078&shcp=b59d6b55",
            "title": "Shakira",
            "subTitle": "@shakira",
            "description": "Las mujeres ya no lloran (Women no longer cry) OUT NOW ❌💧",
            "link": "/@shakira",
            "round": true,
            "playToken": "",
            "keyToken": "",
            "extraInfo": {
              "verified": true,
              "fans": 38700000,
              "likes": 272300000,
              "userId": "168541398546182144",
              "secUid": "MS4wLjABAAAAMTSBCxTaYvqbcRpT924iKILvChaXJEW2t8QEMK3s5NtXENf85cwPjT-biAUnsUfb",
              "relation": 0,
              "video": 306,
              "following": 60,
              "heart": 272300000,
              "digg": 2595
            }
          }
        },
        {
          "cardItem": {
            "id": "142565009246584832",
            "type": 2,
            "cover": "https://p19-pu-sign-useast8.tiktokcdn-us.com/tos-useast5-avt-0068-tx/7f03ace374b5b22da7f064a4fb6fccf6~c5_100x100.jpeg?lk3s=a5d48078&nonce=57583&refresh_token=8bb027fe7453dee6fa4db4899a3aa5f6&x-expires=1725854400&x-signature=h1lnfv29yqnzBFPD8K0lEiNK%2Bok%3D&shp=a5d48078&shcp=b59d6b55",
            "title": "Marshmello",
            "subTitle": "@marshmello",
            "description": "\"Miles on It\" with @Kane Brown out now",
            "link": "/@marshmello",
            "round": true,
            "playToken": "",
            "keyToken": "",
            "extraInfo": {
              "verified": true,
              "fans": 24700000,
              "likes": 241000000,
              "userId": "142565009246584832",
              "secUid": "MS4wLjABAAAAoIjsp53EitSm7GKWMT2VaeDZA25CzmzbvLDyFUJwpCZk7B5PmCoYlO2cV4y_-it9",
              "relation": 0,
              "video": 438,
              "following": 224,
              "heart": 241000000,
              "digg": 4801
            }
          }
        },
        {
          "cardItem": {
            "id": "6881290705605477381",
            "type": 2,
            "cover": "https://p16-pu-sign-useast8.tiktokcdn-us.com/tos-useast8-avt-0068-tx2/f8c7cad75f3a12205d31d6662d2555d5~c5_100x100.jpeg?lk3s=a5d48078&nonce=2898&refresh_token=4888fa1a9ec6bd25c6aa3c0e026f8c33&x-expires=1725854400&x-signature=eewZGCLYKaz3tVK9bhhjAExrXp8%3D&shp=a5d48078&shcp=b59d6b55",
            "title": "Taylor Swift",
            "subTitle": "@taylorswift",
            "description": "This is pretty much just a cat account",
            "link": "/@taylorswift",
            "round": true,
            "playToken": "",
            "keyToken": "",
            "extraInfo": {
              "verified": true,
              "fans": 32800000,
              "likes": 236200000,
              "userId": "6881290705605477381",
              "secUid": "MS4wLjABAAAAqB08cUbXaDWqbD6MCga2RbGTuhfO2EsHayBYx08NDrN7IE3jQuRDNNN6YwyfH6_6",
              "relation": 0,
              "video": 69,
              "following": 0,
              "heart": 236200000,
              "digg": 2204
            }
          }
        },
        {
          "cardItem": {
            "id": "97614653324771328",
            "type": 2,
            "cover": "https://p16-pu-sign-useast8.tiktokcdn-us.com/tos-useast5-avt-0068-tx/7310047350691463214~c5_100x100.jpeg?lk3s=a5d48078&nonce=70833&refresh_token=7c60dff413fbe356b4962714a057c312&x-expires=1725854400&x-signature=uLNfSmHZArviUwR1dzrmgqgE8Q4%3D&shp=a5d48078&shcp=b59d6b55",
            "title": "Selena Gomez",
            "subTitle": "@selenagomez",
            "description": "",
            "link": "/@selenagomez",
            "round": true,
            "playToken": "",
            "keyToken": "",
            "extraInfo": {
              "verified": true,
              "fans": 58200000,
              "likes": 636600000,
              "userId": "97614653324771328",
              "secUid": "MS4wLjABAAAATtFKZYaOb-9nF_w7QRi4y64d45mvuWuwf5ACEd3c6f-GTlfW9rJJlKfV2vWhg0aw",
              "relation": 0,
              "video": 214,
              "following": 73,
              "heart": 636600000,
              "digg": 2468
            }
          }
        },
        {
          "cardItem": {
            "id": "141140993138962432",
            "type": 2,
            "cover": "https://p19-pu-sign-useast8.tiktokcdn-us.com/tos-useast5-avt-0068-tx/cbb09c3e61b5da7899709d4151c8e1ea~c5_100x100.jpeg?lk3s=a5d48078&nonce=52373&refresh_token=b9c5133519cb44d04adc75de9c73405a&x-expires=1725854400&x-signature=2mNuA%2FCx0AeHv%2Fz6PnUhzA5Ir28%3D&shp=a5d48078&shcp=b59d6b55",
            "title": "Post Malone",
            "subTitle": "@postmalone",
            "description": "New album @F-1 Trillion out now 😈🍻",
            "link": "/@postmalone",
            "round": true,
            "playToken": "",
            "keyToken": "",
            "extraInfo": {
              "verified": true,
              "fans": 17500000,
              "likes": 169400000,
              "userId": "141140993138962432",
              "secUid": "MS4wLjABAAAAIAXBSn6tARIqrHDAQM32h-AzSL8yqTbXrZE2HlhpxyctXIAxoYUlBfhmqe-jyzVf",
              "relation": 0,
              "video": 298,
              "following": 45,
              "heart": 169400000,
              "digg": 574
            }
          }
        },
        {
          "cardItem": {
            "id": "6711995161218286598",
            "type": 2,
            "cover": "https://p16-sign-useast2a.tiktokcdn.com/tos-useast2a-avt-0068-euttp/15f7dadbd23b038857c3bec2e465c7d9~c5_100x100.jpeg?lk3s=a5d48078&nonce=80731&refresh_token=bb3886ecc0e1f34a90920ed6ed6f8632&x-expires=1725854400&x-signature=5Ql4zVeMfHd1ifPQ%2F19jLpMnYNQ%3D&shp=a5d48078&shcp=b59d6b55",
            "title": "Sam Smith",
            "subTitle": "@samsmith",
            "description": "In The Lonely Hour (10th Anniversary Edition) out now 🤍",
            "link": "/@samsmith",
            "round": true,
            "playToken": "",
            "keyToken": "",
            "extraInfo": {
              "verified": true,
              "fans": 8900000,
              "likes": 134900000,
              "userId": "6711995161218286598",
              "secUid": "MS4wLjABAAAAo6owCzQgiv9Xm_6O6lJHs85_whEc5JAjUDlmRO4vOH164H4zF2M3PYXBJtPhzXMz",
              "relation": 0,
              "video": 299,
              "following": 3,
              "heart": 134900000,
              "digg": 298
            }
          }
        },
        {
          "cardItem": {
            "id": "224891697648857088",
            "type": 2,
            "cover": "https://p19-pu-sign-useast8.tiktokcdn-us.com/tos-useast5-avt-0068-tx/09a65da8862132cb9dc4efa3b5925abe~c5_100x100.jpeg?lk3s=a5d48078&nonce=20116&refresh_token=2784a3d42e5fdc686b1dbed68618487a&x-expires=1725854400&x-signature=GZ1WEeXowIaaAhIgabwY1dcqMSg%3D&shp=a5d48078&shcp=b59d6b55",
            "title": "Nicki Minaj",
            "subTitle": "@nickiminaj",
            "description": "IT'S TOUR TIME AGAIN!!!! Beginning 9/4 in #GagCityPHILLY",
            "link": "/@nickiminaj",
            "round": true,
            "playToken": "",
            "keyToken": "",
            "extraInfo": {
              "verified": true,
              "fans": 20500000,
              "likes": 156100000,
              "userId": "224891697648857088",
              "secUid": "MS4wLjABAAAAs5jkeWdu5hM55BndQETUnl4rll7H8fthkyz5JmF3P5qKdh_mLcAUVGJ16WPpEI_M",
              "relation": 0,
              "video": 322,
              "following": 9,
              "heart": 156100000,
              "digg": 10600
            }
          }
        },
        {
          "cardItem": {
            "id": "6747935906352907269",
            "type": 2,
            "cover": "https://p16-sign-va.tiktokcdn.com/tos-maliva-avt-0068/7310612651137040390~c5_100x100.jpeg?lk3s=a5d48078&nonce=38693&refresh_token=c0dab723e427ce2d2c86a1e0c28b1b31&x-expires=1725854400&x-signature=Y9WF3NYUhWAlme%2B6HIhR3WPwBRw%3D&shp=a5d48078&shcp=b59d6b55",
            "title": "Gordon Ramsay",
            "subTitle": "@gordonramsayofficial",
            "description": "I cook sometimes too.....\n\nRecipes here 👇🏻",
            "link": "/@gordonramsayofficial",
            "round": true,
            "playToken": "",
            "keyToken": "",
            "extraInfo": {
              "verified": true,
              "fans": 40600000,
              "likes": 685900000,
              "userId": "6747935906352907269",
              "secUid": "MS4wLjABAAAAv3zolJLlWp-WbKXqSZwVSflDdwcbjPADRG-dhb68k30dQjkFpkRs4HiMvWeeIyVv",
              "relation": 0,
              "video": 541,
              "following": 552,
              "heart": 685900000,
              "digg": 948
            }
          }
        },
        {
          "cardItem": {
            "id": "6811538513018012677",
            "type": 2,
            "cover": "https://p16-pu-sign-useast8.tiktokcdn-us.com/tos-useast5-avt-0068-tx/620a4aa08d06806f3ed64dd74c0911c1~c5_100x100.jpeg?lk3s=a5d48078&nonce=57253&refresh_token=3bdcbbcff1c51365588933651973733a&x-expires=1725854400&x-signature=ar5eISaqJaQOUqCXZSLe8ahFTW8%3D&shp=a5d48078&shcp=b59d6b55",
            "title": "Sia",
            "subTitle": "@sia",
            "description": "New album ‘Reasonable Woman’ out now!",
            "link": "/@sia",
            "round": true,
            "playToken": "",
            "keyToken": "",
            "extraInfo": {
              "verified": true,
              "fans": 5300000,
              "likes": 43700000,
              "userId": "6811538513018012677",
              "secUid": "MS4wLjABAAAA0i5Xv3wEpcm2X56kpvnFQCIYNDKgLWR93U-rPWS1G5qPybOzqPs_fKtUZcEcdMb-",
              "relation": 0,
              "video": 201,
              "following": 129,
              "heart": 43700000,
              "digg": 307
            }
          }
        },
        {
          "cardItem": {
            "id": "6746264168812659717",
            "type": 2,
            "cover": "https://p16-pu-sign-useast8.tiktokcdn-us.com/tos-useast5-avt-0068-tx/7310500778328719406~c5_100x100.jpeg?lk3s=a5d48078&nonce=46186&refresh_token=34a50083281c3083081c82326e42b735&x-expires=1725854400&x-signature=F6LHU557SkwF7rheCnRxi%2ByYDYw%3D&shp=a5d48078&shcp=b59d6b55",
            "title": "Terry Crews",
            "subTitle": "@terrycrews",
            "description": "Husband, Father, Actor, Author, Artist, Philanthropist, Athlete",
            "link": "/@terrycrews",
            "round": true,
            "playToken": "",
            "keyToken": "",
            "extraInfo": {
              "verified": true,
              "fans": 24200000,
              "likes": 132100000,
              "userId": "6746264168812659717",
              "secUid": "MS4wLjABAAAAeorUnEgxFuiNspeal1-82s8pfmSKCojvGFhL3fDrspFgBDzg084_uu4KrGLwKVZD",
              "relation": 0,
              "video": 267,
              "following": 117,
              "heart": 132100000,
              "digg": 514
            }
          }
        },
        {
          "cardItem": {
            "id": "132667022575992832",
            "type": 2,
            "cover": "https://p16-pu-sign-useast8.tiktokcdn-us.com/tos-useast5-avt-0068-tx/60af2f54391f7dc317a87869e4bd99b4~c5_100x100.jpeg?lk3s=a5d48078&nonce=553&refresh_token=a9b4c0959fa9be669d283c37b01762ca&x-expires=1725854400&x-signature=lltXLrWhM6HLbTxeetdopjYLER8%3D&shp=a5d48078&shcp=b59d6b55",
            "title": "J Balvin",
            "subTitle": "@jbalvin",
            "description": "RAYO ya disponible ⚡️💿",
            "link": "/@jbalvin",
            "round": true,
            "playToken": "",
            "keyToken": "",
            "extraInfo": {
              "verified": true,
              "fans": 21300000,
              "likes": 125800000,
              "userId": "132667022575992832",
              "secUid": "MS4wLjABAAAAYbp6OaRgezXn4Bp5dmoM2dfBYOASM9M5I3bMLpjp0OdD7Y6JLua2DSAs1EUaVJ45",
              "relation": 0,
              "video": 264,
              "following": 16,
              "heart": 125800000,
              "digg": 999
            }
          }
        },
        {
          "cardItem": {
            "id": "173245838817808384",
            "type": 2,
            "cover": "https://p16-sign-useast2a.tiktokcdn.com/tos-useast2a-avt-0068-euttp/8a30cd8e7c127bd58eb64f003a623ad0~c5_100x100.jpeg?lk3s=a5d48078&nonce=89995&refresh_token=67cd79eff3af74aa3ff115c1ce95c952&x-expires=1725854400&x-signature=Cpqde56zSsXB6SRUlNY6apqpUq0%3D&shp=a5d48078&shcp=b59d6b55",
            "title": "Ed Sheeran",
            "subTitle": "@edsheeran",
            "description": "",
            "link": "/@edsheeran",
            "round": true,
            "playToken": "",
            "keyToken": "",
            "extraInfo": {
              "verified": true,
              "fans": 16000000,
              "likes": 204800000,
              "userId": "173245838817808384",
              "secUid": "MS4wLjABAAAAW-m9le-3IwWQcihDj2Io53yCuEgz0wb1Np_JY3chG8vAsK_fzWmK2NWaz1nzttoD",
              "relation": 0,
              "video": 242,
              "following": 2,
              "heart": 204800000,
              "digg": 239
            }
          }
        },
        {
          "cardItem": {
            "id": "6879693940111901701",
            "type": 2,
            "cover": "https://p19-pu-sign-useast8.tiktokcdn-us.com/tos-useast5-avt-0068-tx/a67f9744439872cde91754ff64b8a97d~c5_100x100.jpeg?lk3s=a5d48078&nonce=65985&refresh_token=ac61d622169602bb5a12965e79373472&x-expires=1725854400&x-signature=IyeJBPnqXvaD5FJMeWGoQMSmsCk%3D&shp=a5d48078&shcp=b59d6b55",
            "title": "BILLIE EILISH",
            "subTitle": "@billieeilish",
            "description": "\"HIT ME HARD AND SOFT\" THE ALBUM\nOUT NOW",
            "link": "/@billieeilish",
            "round": true,
            "playToken": "",
            "keyToken": "",
            "extraInfo": {
              "verified": true,
              "fans": 66300000,
              "likes": 381400000,
              "userId": "6879693940111901701",
              "secUid": "MS4wLjABAAAAQC9D0J9C7zCdiToBJvaCHEZZl1FXTKeeSVoyGQld--0hcxb3lqDTxaSRjByAVlAs",
              "relation": 0,
              "video": 63,
              "following": 66,
              "heart": 381400000,
              "digg": 27900
            }
          }
        },
        {
          "cardItem": {
            "id": "7084315756325782570",
            "type": 2,
            "cover": "https://p16-pu-sign-useast8.tiktokcdn-us.com/tos-useast5-avt-0068-tx/7310670543802335274~c5_100x100.jpeg?lk3s=a5d48078&nonce=50812&refresh_token=de0461163fb573e9bc9885f8cd15034a&x-expires=1725854400&x-signature=X2t1HeDsozsYYPhI9Hc%2B%2FIfxyHE%3D&shp=a5d48078&shcp=b59d6b55",
            "title": "Cooking With Marshmello",
            "subTitle": "@cookingwithmarshmello",
            "description": "Full-Time Chef, Part-Time DJ @Marshmello \nMello cookbook 👇",
            "link": "/@cookingwithmarshmello",
            "round": true,
            "playToken": "",
            "keyToken": "",
            "extraInfo": {
              "verified": true,
              "fans": 4000000,
              "likes": 29300000,
              "userId": "7084315756325782570",
              "secUid": "MS4wLjABAAAAluw--j1UX58BMSQif2sqYZazNsw9gFyEZOdtcoL8OyUVnaJ50fG1Rtt_RvItoFLY",
              "relation": 0,
              "video": 145,
              "following": 2,
              "heart": 29300000,
              "digg": 27
            }
          }
        },
        {
          "cardItem": {
            "id": "59363135073038336",
            "type": 2,
            "cover": "https://p19-pu-sign-useast8.tiktokcdn-us.com/tos-useast8-avt-0068-tx2/9338d2f6b4811c23be1c807c9f6d3072~c5_100x100.jpeg?lk3s=a5d48078&nonce=13849&refresh_token=69a74c0ea499c1d3a8f4a88131620e62&x-expires=1725854400&x-signature=o2NgHaqzUgQg%2BXGH2IL3E0UHe6Y%3D&shp=a5d48078&shcp=b59d6b55",
            "title": "Bebe Rexha",
            "subTitle": "@beberexha",
            "description": "‘IM THE DRAMA’ OUT NOW 💅🏼",
            "link": "/@beberexha",
            "round": true,
            "playToken": "",
            "keyToken": "",
            "extraInfo": {
              "verified": true,
              "fans": 8600000,
              "likes": 146400000,
              "userId": "59363135073038336",
              "secUid": "MS4wLjABAAAAJqzquQqufDOelVGqBf00Skwl42VP-5skR-gDE9XxobPB3gBoz8VFBKj5qWszVMxT",
              "relation": 0,
              "video": 541,
              "following": 281,
              "heart": 146400000,
              "digg": 5546
            }
          }
        },
        {
          "cardItem": {
            "id": "6761177948009956358",
            "type": 2,
            "cover": "https://p19-pu-sign-useast8.tiktokcdn-us.com/tos-useast8-avt-0068-tx2/4f4a6ae12d67e14abd83e7501d3a2447~c5_100x100.jpeg?lk3s=a5d48078&nonce=66337&refresh_token=8d7439cc0a87832a5cad8273cc133f31&x-expires=1725854400&x-signature=8KOIyEwYjAYvYPw%2FWEFlgUy8eCs%3D&shp=a5d48078&shcp=b59d6b55",
            "title": "OZUNA",
            "subTitle": "@ozuna",
            "description": "COSMO OUT NOW !! 💿🖤",
            "link": "/@ozuna",
            "round": true,
            "playToken": "",
            "keyToken": "",
            "extraInfo": {
              "verified": true,
              "fans": 12500000,
              "likes": 55400000,
              "userId": "6761177948009956358",
              "secUid": "MS4wLjABAAAA0YGF2V70cjwyaZwFmztd3l_JeXtxc387kexLBsfwR3ir56bR1f_uEM6GmvNObVoR",
              "relation": 0,
              "video": 83,
              "following": 0,
              "heart": 55400000,
              "digg": 56
            }
          }
        },
        {
          "cardItem": {
            "id": "6930646914937930757",
            "type": 2,
            "cover": "https://p16-pu-sign-useast8.tiktokcdn-us.com/tos-useast5-avt-0068-tx/7328fb2562bbe80e711190d1d7205c01~c5_100x100.jpeg?lk3s=a5d48078&nonce=71991&refresh_token=c87184a08936b358faf0d570d776975f&x-expires=1725854400&x-signature=YlQLaRISqZy77xoPG%2BzpqZC1BTo%3D&shp=a5d48078&shcp=b59d6b55",
            "title": "Billie Eilish Home",
            "subTitle": "@billieeilishhome",
            "description": "\"HIT ME HARD AND SOFT\" THE ALBUM\nOUT NOW",
            "link": "/@billieeilishhome",
            "round": true,
            "playToken": "",
            "keyToken": "",
            "extraInfo": {
              "verified": true,
              "fans": 16400000,
              "likes": 72700000,
              "userId": "6930646914937930757",
              "secUid": "MS4wLjABAAAAfXjcYoR1XGi3ox2_2f_2bZjmlYmOu222adadnAcXD6Y6-qeMTJql-x0xBNlZPkU3",
              "relation": 0,
              "video": 144,
              "following": 1,
              "heart": 72700000,
              "digg": 2
            }
          }
        },
        {
          "cardItem": {
            "id": "6807605867299603461",
            "type": 2,
            "cover": "https://p16-sign.tiktokcdn-us.com/tos-useast5-avt-0068-tx/9741a9d16e737c021e2f34afd8ff1e16~c5_100x100.jpeg?lk3s=a5d48078&nonce=63409&refresh_token=8b8ae79bef6fe6118967b2ac7179120e&x-expires=1725854400&x-signature=H98KLrFuhC%2BA4VLiiHqFOxt%2FsFw%3D&shp=a5d48078&shcp=b59d6b55",
            "title": "chrisbrownofficial",
            "subTitle": "@chrisbrownofficial",
            "description": "",
            "link": "/@chrisbrownofficial",
            "round": true,
            "playToken": "",
            "keyToken": "",
            "extraInfo": {
              "verified": true,
              "fans": 9300000,
              "likes": 34300000,
              "userId": "6807605867299603461",
              "secUid": "MS4wLjABAAAAhozCeV-nMNYOvqcCYMrFkJnoxIF6Pd7oyANhq1CSgEqwG6ISsqFncjElKh6PlUnX",
              "relation": 0,
              "video": 66,
              "following": 0,
              "heart": 34300000,
              "digg": 43
            }
          }
        },
        {
          "cardItem": {
            "id": "6693590239291917318",
            "type": 2,
            "cover": "https://p19-pu-sign-useast8.tiktokcdn-us.com/tos-useast8-avt-0068-tx2/cb95fed604113a82852e3d0875d65f8b~c5_100x100.jpeg?lk3s=a5d48078&nonce=82076&refresh_token=05ad86aba925cd86f34fba7833f04a00&x-expires=1725854400&x-signature=Amh0W4F9HXuL1xMqUGaj7Y1YoCA%3D&shp=a5d48078&shcp=b59d6b55",
            "title": "The Weeknd",
            "subTitle": "@theweeknd",
            "description": "",
            "link": "/@theweeknd",
            "round": true,
            "playToken": "",
            "keyToken": "",
            "extraInfo": {
              "verified": true,
              "fans": 9600000,
              "likes": 49800000,
              "userId": "6693590239291917318",
              "secUid": "MS4wLjABAAAAG3YiXquuv2-O3z4OJpF1-cVHMKpx_JYmOsprbBrmY_MolxRsfK-gkZ4evQpTptGk",
              "relation": 0,
              "video": 131,
              "following": 0,
              "heart": 49800000,
              "digg": 125
            }
          }
        },
        {
          "cardItem": {
            "id": "6611099612067856390",
            "type": 2,
            "cover": "https://p16-pu-sign-useast8.tiktokcdn-us.com/tos-useast5-avt-0068-tx/080d3cfc57d53461445c52e92602b270~c5_100x100.jpeg?lk3s=a5d48078&nonce=51623&refresh_token=7ba28e71c2b5bfd36cdfb931a0807eec&x-expires=1725854400&x-signature=RSx4b12ms7M3jnqaPRGX29VJd2A%3D&shp=a5d48078&shcp=b59d6b55",
            "title": "JLO",
            "subTitle": "@jlo",
            "description": "",
            "link": "/@jlo",
            "round": true,
            "playToken": "",
            "keyToken": "",
            "extraInfo": {
              "verified": true,
              "fans": 17500000,
              "likes": 75100000,
              "userId": "6611099612067856390",
              "secUid": "MS4wLjABAAAA2EvW1E1RwMcww5EY5bG0z2TeJ3dusTXaAKNJBQatp8IGSbOvWYWRm6TIIZ46Q40v",
              "relation": 0,
              "video": 306,
              "following": 216,
              "heart": 75100000,
              "digg": 889
            }
          }
        },
        {
          "cardItem": {
            "id": "6650307866375618566",
            "type": 2,
            "cover": "https://p19-pu-sign-useast8.tiktokcdn-us.com/tos-useast5-avt-0068-tx/c36923d444cde1d6dab083878765f242~c5_100x100.jpeg?lk3s=a5d48078&nonce=63360&refresh_token=9f64e2ee2a05ff145742fe439b61153a&x-expires=1725854400&x-signature=QsyYTSvn23IkdT9%2F5GG9eWJ5NBw%3D&shp=a5d48078&shcp=b59d6b55",
            "title": "jaredleto",
            "subTitle": "@jaredleto",
            "description": "SEASONS WORLD TOUR - TICKETS, VIP & MORE INFO 👇🏻",
            "link": "/@jaredleto",
            "round": true,
            "playToken": "",
            "keyToken": "",
            "extraInfo": {
              "verified": true,
              "fans": 2000000,
              "likes": 16600000,
              "userId": "6650307866375618566",
              "secUid": "MS4wLjABAAAA-10td9W7IbRRsU71B47h077wRDPle3kuB2rfdEQRiy-noYMxiz5Bh0C2jO8VYGJ3",
              "relation": 0,
              "video": 218,
              "following": 2,
              "heart": 16600000,
              "digg": 174
            }
          }
        },
        {
          "cardItem": {
            "id": "7050076999289521158",
            "type": 2,
            "cover": "https://p19-sign.tiktokcdn-us.com/tos-useast5-avt-0068-tx/59d86801aec13e838ff4542960db504e~c5_100x100.jpeg?lk3s=a5d48078&nonce=6311&refresh_token=cc3342b7ae101daaf631e9fd63cb391b&x-expires=1725854400&x-signature=0z1YXG0UD3M3NZrjL3UoxUSIO2M%3D&shp=a5d48078&shcp=b59d6b55",
            "title": "Justin Timberlake",
            "subTitle": "@justintimberlake",
            "description": "Jessica Biel’s boyfriend",
            "link": "/@justintimberlake",
            "round": true,
            "playToken": "",
            "keyToken": "",
            "extraInfo": {
              "verified": true,
              "fans": 3500000,
              "likes": 20400000,
              "userId": "7050076999289521158",
              "secUid": "MS4wLjABAAAAFFnnU79C5yrDL_Sm1pWwOGAPt3fFpfCDxP9HgGgn16dSovFSSRpfTdV9B0cURnxP",
              "relation": 0,
              "video": 83,
              "following": 133,
              "heart": 20400000,
              "digg": 549
            }
          }
        },
        {
          "cardItem": {
            "id": "159398380291555328",
            "type": 2,
            "cover": "https://p19-pu-sign-useast8.tiktokcdn-us.com/tos-useast5-avt-0068-tx/e065bd760fb46e0afeda1870fed11d80~c5_100x100.jpeg?lk3s=a5d48078&nonce=40777&refresh_token=9f7fb6ca38ab724df0f1bb3aebf12d5b&x-expires=1725854400&x-signature=IfcC%2Fxo%2Byalp5N56DuPmQlaMhxc%3D&shp=a5d48078&shcp=b59d6b55",
            "title": "Bruno Mars",
            "subTitle": "@brunomars",
            "description": "Die With A Smile 💙❤️ OUT NOW",
            "link": "/@brunomars",
            "round": true,
            "playToken": "",
            "keyToken": "",
            "extraInfo": {
              "verified": true,
              "fans": 10600000,
              "likes": 36300000,
              "userId": "159398380291555328",
              "secUid": "MS4wLjABAAAA06euMtqRvuACJv5KhDdrE3qY5de2t6uDGKt3j0xe5bzqoPk-x1IFhG8gxHAfaxmH",
              "relation": 0,
              "video": 40,
              "following": 3,
              "heart": 36300000,
              "digg": 9
            }
          }
        },
        {
          "cardItem": {
            "id": "7048381615760262149",
            "type": 2,
            "cover": "https://p16-sign-va.tiktokcdn.com/tos-maliva-avt-0068/725c03323264553ec29bba546ab94c05~c5_100x100.jpeg?lk3s=a5d48078&nonce=75077&refresh_token=c2b83d3421df931b7150ca8aee9579e9&x-expires=1725854400&x-signature=j9T2%2BnxfDBiMShXYOmwDKYgl6vk%3D&shp=a5d48078&shcp=b59d6b55",
            "title": "Peso Pluma",
            "subTitle": "@therealpesopluma",
            "description": "La Doble P",
            "link": "/@therealpesopluma",
            "round": true,
            "playToken": "",
            "keyToken": "",
            "extraInfo": {
              "verified": true,
              "fans": 6100000,
              "likes": 20800000,
              "userId": "7048381615760262149",
              "secUid": "MS4wLjABAAAALcXJUfDCejabJFvyniO0CbGSKPkbDS7UQhgbhx_G3Whx5FfxdWvy8JNzcLOrIoqB",
              "relation": 0,
              "video": 27,
              "following": 9,
              "heart": 20800000,
              "digg": 1151
            }
          }
        },
        {
          "cardItem": {
            "id": "6621955904844021765",
            "type": 2,
            "cover": "https://p16-pu-sign-useast8.tiktokcdn-us.com/tos-useast5-avt-0068-tx/e13dfb42506c14e57d234719374265d6~c5_100x100.jpeg?lk3s=a5d48078&nonce=74425&refresh_token=1a6a8675a69cf9054584cc7d54275c2a&x-expires=1725854400&x-signature=Km84moraiYDzAemJC8cT9rusCkw%3D&shp=a5d48078&shcp=b59d6b55",
            "title": "Rihanna",
            "subTitle": "@rihanna",
            "description": "",
            "link": "/@rihanna",
            "round": true,
            "playToken": "",
            "keyToken": "",
            "extraInfo": {
              "verified": true,
              "fans": 14400000,
              "likes": 54300000,
              "userId": "6621955904844021765",
              "secUid": "MS4wLjABAAAAd04PpJrQJrRv5QpeLCz-tj41zTwuemXz6WBpyycnVNGeYqJjlOzJ5fpV9QWK5h4B",
              "relation": 0,
              "video": 19,
              "following": 0,
              "heart": 54300000,
              "digg": 1
            }
          }
        }
      ],
      "pageState": {
        "regionAppId": 1233,
        "os": "mac",
        "region": "US",
        "baseURL": "m.tiktok.com",
        "appType": "m",
        "fullUrl": "https://www.tiktok.com/node/share/discover"
      }
    },
    {
      "exploreList": [
        {
          "cardItem": {
            "id": "7223391880308850731",
            "type": 3,
            "cover": "https://p16-amd-va.tiktokcdn.com/obj/musically-maliva-obj/0d93d1110a4def67d8dd9cd57d0e7884.jpeg?shp=81f88b70&shcp=-",
            "title": "#touchdowndeals",
            "subTitle": "13.2M views",
            "description": "Score big with an unbeatable selection of Collectibles, Toys &amp; Hobbies, and Sports &amp; Outdoors. Only on TikTok Shop!",
            "link": "/tag/touchdowndeals",
            "round": false,
            "playToken": "",
            "keyToken": "",
            "extraInfo": {
              "views": 13200000,
              "challengeId": "7223391880308850731",
              "challengeName": "touchdowndeals"
            }
          }
        },
        {
          "cardItem": {
            "id": "1604297750222853",
            "type": 3,
            "cover": "https://p16-amd-va.tiktokcdn.com/obj/musically-maliva-obj/009a66f069c7810ce536ac4c307c9f74.png?shp=81f88b70&shcp=-",
            "title": "#longervideos",
            "subTitle": "280.9B views",
            "description": "Try longer videos (videos longer than 1 minute)! Create longer videos to express yourself and share more of your story on TikTok",
            "link": "/tag/longervideos",
            "round": false,
            "playToken": "",
            "keyToken": "",
            "extraInfo": {
              "views": 280900000000,
              "challengeId": "1604297750222853",
              "challengeName": "longervideos"
            }
          }
        },
        {
          "cardItem": {
            "id": "235463",
            "type": 3,
            "title": "#1min",
            "subTitle": "7.3B views",
            "description": "",
            "link": "/tag/1min",
            "round": false,
            "playToken": "",
            "keyToken": "",
            "extraInfo": {
              "views": 7300000000,
              "challengeId": "235463",
              "challengeName": "1min"
            }
          }
        },
        {
          "cardItem": {
            "id": "1591463963924482",
            "type": 3,
            "cover": "https://p16-amd-va.tiktokcdn.com/obj/musically-maliva-obj/edceef9195bb64a48bc57effaa63894c.png?shp=81f88b70&shcp=-",
            "title": "#PetsOfTikTok",
            "subTitle": "139B views",
            "description": "Here's to all the #PetsOfTikTok.",
            "link": "/tag/PetsOfTikTok",
            "round": false,
            "playToken": "",
            "keyToken": "",
            "extraInfo": {
              "views": 139000000000,
              "challengeId": "1591463963924482",
              "challengeName": "PetsOfTikTok"
            }
          }
        },
        {
          "cardItem": {
            "id": "1603828529424386",
            "type": 3,
            "cover": "https://p16-amd-va.tiktokcdn.com/obj/musically-maliva-obj/bc43b89fed5808107f6ecfc274f36a90.jpeg?shp=81f88b70&shcp=-",
            "title": "#couplestiktok",
            "subTitle": "64.5B views",
            "description": "Cute pics, dinner dates, and more. Here's to the all the couples on TikTok.",
            "link": "/tag/couplestiktok",
            "round": false,
            "playToken": "",
            "keyToken": "",
            "extraInfo": {
              "views": 64500000000,
              "challengeId": "1603828529424386",
              "challengeName": "couplestiktok"
            }
          }
        },
        {
          "cardItem": {
            "id": "39658",
            "type": 3,
            "cover": "https://p16-amd-va.tiktokcdn.com/obj/musically-maliva-obj/feb4c89b2b972560362fbf43209635bc.png?shp=81f88b70&shcp=-",
            "title": "#makeuptutorial",
            "subTitle": "168.5B views",
            "description": "Show us your #MakeupTutorial.",
            "link": "/tag/makeuptutorial",
            "round": false,
            "playToken": "",
            "keyToken": "",
            "extraInfo": {
              "views": 168500000000,
              "challengeId": "39658",
              "challengeName": "makeuptutorial"
            }
          }
        },
        {
          "cardItem": {
            "id": "467758",
            "type": 3,
            "cover": "https://p16-amd-va.tiktokcdn.com/obj/musically-maliva-obj/5dc8ae8243bd7b028110837bf3b03e8f.jpeg?shp=81f88b70&shcp=-",
            "title": "#WrestleMania",
            "subTitle": "20.1B views",
            "description": "WrestleMania goes Hollywood for a special two-night Premium Live Event, Saturday, April 1, and Sunday, April 2, at 8 ET/5 PT, streaming live on Peacock in the United States and on WWE Network everywhere else.",
            "link": "/tag/WrestleMania",
            "round": false,
            "playToken": "",
            "keyToken": "",
            "extraInfo": {
              "views": 20100000000,
              "challengeId": "467758",
              "challengeName": "WrestleMania"
            }
          }
        },
        {
          "cardItem": {
            "id": "170127",
            "type": 3,
            "cover": "https://p16-amd-va.tiktokcdn.com/obj/musically-maliva-obj/b29edd485bd84eddb691792f7857cb0f.jpeg?shp=81f88b70&shcp=-",
            "title": "#springcleaning",
            "subTitle": "4.1B views",
            "description": "Get ready for spring cleaning by refreshing and restocking your home with these essentials!",
            "link": "/tag/springcleaning",
            "round": false,
            "playToken": "",
            "keyToken": "",
            "extraInfo": {
              "views": 4100000000,
              "challengeId": "170127",
              "challengeName": "springcleaning"
            }
          }
        },
        {
          "cardItem": {
            "id": "39786843",
            "type": 3,
            "cover": "https://p16-amd-va.tiktokcdn.com/obj/musically-maliva-obj/abcb3145d1adc7a752b69105abf62ae8.png?shp=81f88b70&shcp=-",
            "title": "#tiptok",
            "subTitle": "3.9B views",
            "description": "Whether it's a life hack, secret you ought to know, or an incredible tutorial, here's to #TipTok.",
            "link": "/tag/tiptok",
            "round": false,
            "playToken": "",
            "keyToken": "",
            "extraInfo": {
              "views": 3900000000,
              "challengeId": "39786843",
              "challengeName": "tiptok"
            }
          }
        },
        {
          "cardItem": {
            "id": "1334984",
            "type": 3,
            "cover": "https://p16-sg.tiktokcdn.com/obj/tiktok-obj/c047491662078c775c566c83fdddbf99.png?shp=81f88b70&shcp=-",
            "title": "#diyproject",
            "subTitle": "58.4B views",
            "description": "Looking to DIY? Find a community full of tips and tricks to guide you. Your next project starts on TikTok.",
            "link": "/tag/diyproject",
            "round": false,
            "playToken": "",
            "keyToken": "",
            "extraInfo": {
              "views": 58400000000,
              "challengeId": "1334984",
              "challengeName": "diyproject"
            }
          }
        }
      ],
      "pageState": {
        "regionAppId": 1233,
        "os": "mac",
        "region": "US",
        "baseURL": "m.tiktok.com",
        "appType": "m",
        "fullUrl": "https://www.tiktok.com/node/share/discover"
      }
    },
    {
      "exploreList": [
        {
          "cardItem": {
            "id": "6740248251825391617",
            "type": 1,
            "round": false,
            "playToken": "",
            "keyToken": "",
            "cover": "https://p16-sg.tiktokcdn.com/aweme/100x100/tos-alisg-v-2774/o8yiAEohEAkLAsdWEYAUpABIAsfDFotauwlzIh.jpeg",
            "title": "Forever",
            "subTitle": "3.3M videos",
            "description": "Labrinth",
            "link": "/music/Forever-6740248251825391617",
            "extraInfo": {
              "musicId": "6740248251825391617",
              "playUrl": "https://sf16-ies-music-sg.tiktokcdn.com/obj/tos-alisg-ve-2774/5064f52a3d8f4efcae356cfb758c25d7",
              "posts": 3300000
            }
          }
        },
        {
          "cardItem": {
            "id": "5000000001008467945",
            "type": 1,
            "round": false,
            "playToken": "",
            "keyToken": "",
            "cover": "https://p16-sg.tiktokcdn.com/aweme/100x100/tos-alisg-v-2774/78ab24605f01407ca5a657502d22d021.jpeg",
            "title": "Quinceañera",
            "subTitle": "48.1K videos",
            "description": "Banda Machos",
            "link": "/music/Quinceañera-5000000001008467945",
            "extraInfo": {
              "musicId": "5000000001008467945",
              "playUrl": "https://sf16-ies-music-sg.tiktokcdn.com/obj/tos-alisg-ve-2774/9ad29db610e84eff88a3fc42db241c80",
              "posts": 48100
            }
          }
        },
        {
          "cardItem": {
            "id": "222453230176251905",
            "type": 1,
            "round": false,
            "playToken": "",
            "keyToken": "",
            "cover": "https://p16-sg.tiktokcdn.com/aweme/100x100/tos-alisg-v-2774/d33ece898368470bbcc14c8e2220f5a4.jpeg",
            "title": "Hasta la Raíz",
            "subTitle": "235.4K videos",
            "description": "Natalia Lafourcade",
            "link": "/music/Hasta-la-Raíz-222453230176251905",
            "extraInfo": {
              "musicId": "222453230176251905",
              "playUrl": "https://sf16-ies-music-sg.tiktokcdn.com/obj/tos-alisg-ve-2774/6136a745a84544b18680c096d6be8de0",
              "posts": 235400
            }
          }
        },
        {
          "cardItem": {
            "id": "6990410706927536902",
            "type": 1,
            "round": false,
            "playToken": "",
            "keyToken": "",
            "cover": "https://p16-sg.tiktokcdn.com/aweme/100x100/tos-alisg-v-2774/ogsDAI8EvEUVdEPiAsd7AYrpAWiBASAB8Zgnb.jpeg",
            "title": "The Assignment",
            "subTitle": "528.4K videos",
            "description": "Tay Money",
            "link": "/music/The-Assignment-6990410706927536902",
            "extraInfo": {
              "musicId": "6990410706927536902",
              "playUrl": "https://sf16-ies-music-sg.tiktokcdn.com/obj/tos-alisg-ve-2774/oACzFe3emebx7aPGQGDnZqbsobTOAq99DgxjDz",
              "posts": 528400
            }
          }
        },
        {
          "cardItem": {
            "id": "6872482756727670785",
            "type": 1,
            "round": false,
            "playToken": "",
            "keyToken": "",
            "cover": "https://p16-sg.tiktokcdn.com/aweme/100x100/tos-alisg-v-2774/23a0eff8a40648aa95af4ef1ffc85e58.jpeg",
            "title": "Triple S",
            "subTitle": "164.7K videos",
            "description": "YN Jay & Louie Ray",
            "link": "/music/Triple-S-6872482756727670785",
            "extraInfo": {
              "musicId": "6872482756727670785",
              "playUrl": "https://sf16-ies-music-sg.tiktokcdn.com/obj/tos-alisg-ve-2774/31612d82feab424686af9887c29332ab",
              "posts": 164700
            }
          }
        },
        {
          "cardItem": {
            "id": "6914711053674760193",
            "type": 1,
            "round": false,
            "playToken": "",
            "keyToken": "",
            "cover": "https://p16-sg.tiktokcdn.com/aweme/100x100/tos-alisg-v-2774/o0I4IQEC0DCjfiARAHFiBZmABtng1BUNIrfVoE.jpeg",
            "title": "drivers license",
            "subTitle": "906.7K videos",
            "description": "Olivia Rodrigo",
            "link": "/music/drivers-license-6914711053674760193",
            "extraInfo": {
              "musicId": "6914711053674760193",
              "playUrl": "https://sf16-ies-music-sg.tiktokcdn.com/obj/tos-alisg-ve-2774/oQjQefwHgkAagjaCxRfM8Dszx3FW7nPAVNaMwg",
              "posts": 906700
            }
          }
        },
        {
          "cardItem": {
            "id": "6907566405198841857",
            "type": 1,
            "round": false,
            "playToken": "",
            "keyToken": "",
            "cover": "https://p16-sg.tiktokcdn.com/aweme/100x100/tos-alisg-v-2774/34b723d31d6d4cd49f5ef94a969321c4.jpeg",
            "title": "Afterglow",
            "subTitle": "222K videos",
            "description": "Ed Sheeran",
            "link": "/music/Afterglow-6907566405198841857",
            "extraInfo": {
              "musicId": "6907566405198841857",
              "playUrl": "https://sf16-ies-music-sg.tiktokcdn.com/obj/tos-alisg-ve-2774/e167d044a16d40a5a61cb2ff86e6c6ce",
              "posts": 222000
            }
          }
        },
        {
          "cardItem": {
            "id": "6753170536311818242",
            "type": 1,
            "round": false,
            "playToken": "",
            "keyToken": "",
            "cover": "https://p16-sg.tiktokcdn.com/aweme/100x100/tos-alisg-v-2774/35467ed0648143179b29ab41275f0c6f.jpeg",
            "title": "Holly Jolly Christmas",
            "subTitle": "98.9K videos",
            "description": "Michael Bublé",
            "link": "/music/Holly-Jolly-Christmas-6753170536311818242",
            "extraInfo": {
              "musicId": "6753170536311818242",
              "playUrl": "https://sf16-ies-music-sg.tiktokcdn.com/obj/tos-alisg-ve-2774/64fa766832274eb386fe860ae4170db3",
              "posts": 98900
            }
          }
        },
        {
          "cardItem": {
            "id": "6878744350931634950",
            "type": 1,
            "round": false,
            "playToken": "",
            "keyToken": "",
            "cover": "https://p16-sg.tiktokcdn.com/aweme/100x100/tos-alisg-v-2774/7af41feeb9d8449094a0e6c437e87db5.jpeg",
            "title": "真夜中のドア〜stay with me",
            "subTitle": "426.4K videos",
            "description": "松原みき",
            "link": "/music/真夜中のドア〜stay-with-me-6878744350931634950",
            "extraInfo": {
              "musicId": "6878744350931634950",
              "playUrl": "https://sf16-ies-music-sg.tiktokcdn.com/obj/tos-alisg-ve-2774/oIDD6GTCeh5DaP8zXfUEb5FgqPAbpM05jVeIkn",
              "posts": 426400
            }
          }
        }
      ],
      "pageState": {
        "regionAppId": 1233,
        "os": "mac",
        "region": "US",
        "baseURL": "m.tiktok.com",
        "appType": "m",
        "fullUrl": "https://www.tiktok.com/node/share/discover"
      }
    }
  ]
}
