{
  "body": [
    {
      "exploreList": [
        {
          "cardItem": {
            "id": "5831967",
            "type": 2,
            "cover": "https://p16-sign-va.tiktokcdn.com/musically-maliva-obj/0a0242e5f906bf9301f859c568b5ecc4~c5_100x100.jpeg?x-expires=1615294800&x-signature=NrtyLU7a1GTcg9zi2wHrng2Y79Q%3D",
            "title": "charli d’amelio",
            "subTitle": "@charlidamelio",
            "description": "shop my pura vida pack :)",
            "link": "/@charlidamelio",
            "round": true,
            "playToken": "",
            "keyToken": "",
            "extraInfo": {
              "verified": true,
              "fans": 109500000,
              "likes": "8800000000",
              "userId": "5831967",
              "secUid": "MS4wLjABAAAA-VASjiXTh7wDDyXvjk10VFhMWUAoxr8bgfO1kAL1-9s",
              "relation": -1,
              "roomId": ""
            }
          }
        },
        {
          "cardItem": {
            "id": "6703550784929793030",
            "type": 2,
            "cover": "https://p16-sign-va.tiktokcdn.com/tos-maliva-avt-0068/ffbb5c423f29519c70b0e388642ef53f~c5_100x100.jpeg?x-expires=1615294800&x-signature=hvCtdrndyjK8pqSRgRMOjWmsFvk%3D",
            "title": "addison rae",
            "subTitle": "@addisonre",
            "description": "you look lost, follow me",
            "link": "/@addisonre",
            "round": true,
            "playToken": "",
            "keyToken": "",
            "extraInfo": {
              "verified": true,
              "fans": 77700000,
              "likes": "5000000000",
              "userId": "6703550784929793030",
              "secUid": "MS4wLjABAAAAVjQK614JSGmZVT3EVAiSDfznaBJOVfWPrtqDsQ9YxU368ewQrTyyEOb3OtJb4xCI",
              "relation": -1,
              "roomId": ""
            }
          }
        },
        {
          "cardItem": {
            "id": "6748458643983238149",
            "type": 2,
            "cover": "https://p16-sign-va.tiktokcdn.com/tos-maliva-avt-0068/accb264b992730e59b1013f1307ae156~c5_100x100.jpeg?x-expires=1615294800&x-signature=5%2FZ%2FOGlRJM%2BFS9%2FJHOFdIoDfUrc%3D",
            "title": "Bella Poarch",
            "subTitle": "@bellapoarch",
            "description": "🇵🇭\n💕Thank you for 58 mil💕\n bellapoarch@bas.media",
            "link": "/@bellapoarch",
            "round": true,
            "playToken": "",
            "keyToken": "",
            "extraInfo": {
              "verified": true,
              "fans": 58400000,
              "likes": "1200000000",
              "userId": "6748458643983238149",
              "secUid": "MS4wLjABAAAAIQGNoHByQvokcLbWCGnIfas0OV2nctsZnRFbN7eB04xt-9usrHe3UvXJRZLxBWlJ",
              "relation": -1,
              "roomId": ""
            }
          }
        },
        {
          "cardItem": {
            "id": "6806777679287698437",
            "type": 2,
            "cover": "https://p16-sign-va.tiktokcdn.com/tos-maliva-avt-0068/c306aa94f5e1642e14d94d72f106ca23~c5_100x100.jpeg?x-expires=1615294800&x-signature=uAO%2FcGO8tHojAlXW1NKqJgtZpVY%3D",
            "title": "Kareem & Fifi",
            "subTitle": "@dontstopmeowing",
            "description": "Follow us on Instagram! 👆\nTysm for 4.3m 😻\nMerch is located on our website👇",
            "link": "/@dontstopmeowing",
            "round": true,
            "playToken": "",
            "keyToken": "",
            "extraInfo": {
              "verified": false,
              "fans": 4400000,
              "likes": "112300000",
              "userId": "6806777679287698437",
              "secUid": "MS4wLjABAAAAa5aQB5MZqHA1xweEWUy_I4WmOHHS_uiHlsoX2HJ4Mc8uHiAnsTz9HVn8fhtz3Oo2",
              "relation": -1,
              "roomId": ""
            }
          }
        },
        {
          "cardItem": {
            "id": "6689853951518737414",
            "type": 2,
            "cover": "https://p16-sign-va.tiktokcdn.com/musically-maliva-obj/1661392172869638~c5_100x100.jpeg?x-expires=1615294800&x-signature=dO%2FyVXRvNvJt4%2FVTWKwd6ej48c0%3D",
            "title": "PARTY SHIRT ",
            "subTitle": "@partyshirt",
            "description": "music duo, ivy and x\nour journey to be the greatest\n📩 ps@unitedtalent.com\nYT⬇️",
            "link": "/@partyshirt",
            "round": true,
            "playToken": "",
            "keyToken": "",
            "extraInfo": {
              "verified": true,
              "fans": 15600000,
              "likes": "313600000",
              "userId": "6689853951518737414",
              "secUid": "MS4wLjABAAAAJ1mMLhFaCd92Xesh4Sd4SeeGjTFp9pFvUqpIGs3mQsPEJCSpHf5YnVVUPbydFszP",
              "relation": -1,
              "roomId": ""
            }
          }
        },
        {
          "cardItem": {
            "id": "6775033566016963589",
            "type": 2,
            "cover": "https://p16-sign-va.tiktokcdn.com/musically-maliva-obj/1655224972112917~c5_100x100.jpeg?x-expires=1615294800&x-signature=eQXOA%2F7iCtwxQjok1Li11Eg22jk%3D",
            "title": "noah beck",
            "subTitle": "@noahbeck",
            "description": "ur luv’d<3\ndo what makes you happy\nbusiness: noah@talentxent.com",
            "link": "/@noahbeck",
            "round": true,
            "playToken": "",
            "keyToken": "",
            "extraInfo": {
              "verified": true,
              "fans": 25800000,
              "likes": "1600000000",
              "userId": "6775033566016963589",
              "secUid": "MS4wLjABAAAAt0f_-5VFQSVpQ19iDpehvCPN4UgDV-Y6SOYicZxKDjgKfKzUdnRZFTDe3GMdiGJd",
              "relation": -1,
              "roomId": ""
            }
          }
        },
        {
          "cardItem": {
            "id": "6633503451764916230",
            "type": 2,
            "cover": "https://p16-sign-va.tiktokcdn.com/musically-maliva-obj/ed3e7415025dfea2cc63224734e2901a~c5_100x100.jpeg?x-expires=1615294800&x-signature=M%2BxOEK1ruhczlrk1IOAUMOH0Yyw%3D",
            "title": "spencer 💅",
            "subTitle": "@spencewuah",
            "description": "email: spencewuah@viralnationtalent.com\ncashapp: justtspencerr\nBLM\nhe/him",
            "link": "/@spencewuah",
            "round": true,
            "playToken": "",
            "keyToken": "",
            "extraInfo": {
              "verified": true,
              "fans": 9200000,
              "likes": "853200000",
              "userId": "6633503451764916230",
              "secUid": "MS4wLjABAAAAzbF6IBx-W0xyGU5L3mkIOWxzj_SG6HMPimz-RVXRv4Q3a2wohtnHSo4qXjfXxD8n",
              "relation": -1,
              "roomId": ""
            }
          }
        },
        {
          "cardItem": {
            "id": "6864320287262540806",
            "type": 2,
            "cover": "https://p16-sign-va.tiktokcdn.com/tos-maliva-avt-0068/792ea632095eeadee808c9c3027d5cac~c5_100x100.jpeg?x-expires=1615294800&x-signature=mSTkTvdhHlvliPqU75s7FhNfDqs%3D",
            "title": "Oneya D’Amelio",
            "subTitle": "@angryreactions",
            "description": "Business email OneyaJohnson@yahoo.com\nChat with me on Cameo @angryreactions 😁💕",
            "link": "/@angryreactions",
            "round": true,
            "playToken": "",
            "keyToken": "",
            "extraInfo": {
              "verified": true,
              "fans": 15400000,
              "likes": "283300000",
              "userId": "6864320287262540806",
              "secUid": "MS4wLjABAAAAOdQG_-7zS4-FKDO5YbQrmPcN80IvFXDyD2rV5aLQJYfBqDW4zJppR1rTS1ZvH0Rq",
              "relation": -1,
              "roomId": ""
            }
          }
        },
        {
          "cardItem": {
            "id": "6587535917023182853",
            "type": 2,
            "cover": "https://p16-sign-va.tiktokcdn.com/tos-maliva-avt-0068/22119f863eae7e35852cdf7b41efe20a~c5_100x100.jpeg?x-expires=1615294800&x-signature=blxKVRwRC4KDdhODMgnAghHtgNI%3D",
            "title": "Daniel LaBelle",
            "subTitle": "@daniel.labelle",
            "description": "",
            "link": "/@daniel.labelle",
            "round": true,
            "playToken": "",
            "keyToken": "",
            "extraInfo": {
              "verified": true,
              "fans": 16400000,
              "likes": "357800000",
              "userId": "6587535917023182853",
              "secUid": "MS4wLjABAAAA2sCfGnqRN1c0jn5CxmbkNDWyI39XImwnfb_IJQGE1i-cRUcgSJv_un0Cje3g39Mn",
              "relation": -1,
              "roomId": ""
            }
          }
        },
        {
          "cardItem": {
            "id": "6646929788928311301",
            "type": 2,
            "cover": "https://p16-sign-va.tiktokcdn.com/tos-maliva-avt-0068/9b72c02f539e067e45c3064d49a9129a~c5_100x100.jpeg?x-expires=1615294800&x-signature=P1gRhw580JpGBawvBc6KwcCCsFo%3D",
            "title": "Zeth",
            "subTitle": "@7eth",
            "description": "CEO of Mingo Gang\n🦩\nCan we get to 250k Subs?\n⬇️",
            "link": "/@7eth",
            "round": true,
            "playToken": "",
            "keyToken": "",
            "extraInfo": {
              "verified": false,
              "fans": 5000000,
              "likes": "99900000",
              "userId": "6646929788928311301",
              "secUid": "MS4wLjABAAAAPqmaZRhBQj_QokOQjsJZ1uflWek6Sp2TgGJfOwCv6NHdQRDsxkuo9azXCwrXowSI",
              "relation": -1,
              "roomId": ""
            }
          }
        },
        {
          "cardItem": {
            "id": "3777553",
            "type": 2,
            "cover": "https://p16-sign-va.tiktokcdn.com/musically-maliva-obj/52d5a27a08dee116adc908aa715bd31b~c5_100x100.jpeg?x-expires=1615294800&x-signature=%2BSl3B5nj70BVqG%2FQpN7zCb5akWo%3D",
            "title": "Michael Le",
            "subTitle": "@justmaiko",
            "description": "subscribe to my youtube if you read this💙🙂",
            "link": "/@justmaiko",
            "round": true,
            "playToken": "",
            "keyToken": "",
            "extraInfo": {
              "verified": true,
              "fans": 45900000,
              "likes": "1300000000",
              "userId": "3777553",
              "secUid": "MS4wLjABAAAA6klSQuO9zZPMccWbBdMw9p-cfmr8NbpmXUQHfj6p6f8",
              "relation": -1,
              "roomId": ""
            }
          }
        },
        {
          "cardItem": {
            "id": "6658722935124328453",
            "type": 2,
            "cover": "https://p16-sign-va.tiktokcdn.com/tos-maliva-avt-0068/63112704f1f3c1fc80cb317da466c77d~c5_100x100.jpeg?x-expires=1615294800&x-signature=kmlSeVF0MDg2y5IBv1q8VnNrfQE%3D",
            "title": "lil nas x",
            "subTitle": "@lilnasx",
            "description": "THE NUMBER 1 SONG IN THE WORLD “HOLIDAY” IS OUT NOW! ❄️",
            "link": "/@lilnasx",
            "round": true,
            "playToken": "",
            "keyToken": "",
            "extraInfo": {
              "verified": true,
              "fans": 9700000,
              "likes": "227800000",
              "userId": "6658722935124328453",
              "secUid": "MS4wLjABAAAAS9ciBdtH3kzTIz09dQVBybwPFnbjO-Q5FqkXdQ34LLBTkIi6hLYYwtYLDwjh0PaY",
              "relation": -1,
              "roomId": ""
            }
          }
        },
        {
          "cardItem": {
            "id": "100481652413403136",
            "type": 2,
            "cover": "https://p16-sign-va.tiktokcdn.com/musically-maliva-obj/1666341926624261~c5_100x100.jpeg?x-expires=1615294800&x-signature=YgiQRa%2BsomlndMvNQooWStsgs1E%3D",
            "title": "ROMINA",
            "subTitle": "@rominagafur",
            "description": "NYC🇺🇸\nbiz: businessromina@gmail.com",
            "link": "/@rominagafur",
            "round": true,
            "playToken": "",
            "keyToken": "",
            "extraInfo": {
              "verified": true,
              "fans": 19000000,
              "likes": "818400000",
              "userId": "100481652413403136",
              "secUid": "MS4wLjABAAAAb5pDtGWPwD-auGsAwB0D54bny8bLj-Fva3PI9NtSdg7kNLsUneU1nFasTk0uzI-L",
              "relation": -1,
              "roomId": ""
            }
          }
        },
        {
          "cardItem": {
            "id": "6746417382892176389",
            "type": 2,
            "cover": "https://p16-sign-va.tiktokcdn.com/tos-maliva-avt-0068/4e0b933e2ee157ead2bdaea0ef0fee81~c5_100x100.jpeg?x-expires=1615294800&x-signature=bomM8sz6zDP0GG858b%2F8pRm30zE%3D",
            "title": "KEEMOKAZI",
            "subTitle": "@keemokazi",
            "description": "Following back on IG for the next 24 hours ↖️\n“ARAB MONEY” out now 💰⬇️",
            "link": "/@keemokazi",
            "round": true,
            "playToken": "",
            "keyToken": "",
            "extraInfo": {
              "verified": true,
              "fans": 15900000,
              "likes": "594700000",
              "userId": "6746417382892176389",
              "secUid": "MS4wLjABAAAAwOIa5vSA9Qy40SlT9q4Y9LhCTR__vPTjLQ06IAjfcGlC8NPTplo-RjwW0ljl0jsw",
              "relation": -1,
              "roomId": ""
            }
          }
        },
        {
          "cardItem": {
            "id": "6539853526925841423",
            "type": 2,
            "cover": "https://p16-sign-va.tiktokcdn.com/tos-maliva-avt-0068/57d69d70a507a2d7e6262b22c5748417~c5_100x100.jpeg?x-expires=1615294800&x-signature=Pzhw5QxNB8aZeUUclhGRHsVyzYY%3D",
            "title": "dixie",
            "subTitle": "@dixiedamelio",
            "description": "",
            "link": "/@dixiedamelio",
            "round": true,
            "playToken": "",
            "keyToken": "",
            "extraInfo": {
              "verified": true,
              "fans": 49500000,
              "likes": "2900000000",
              "userId": "6539853526925841423",
              "secUid": "MS4wLjABAAAAiGb8Q0kNIr7hAamylsgJcqAFs7OUVuhBY6NCpHt6ujbxheY7Y0Hpc15V6mgUxjaN",
              "relation": -1,
              "roomId": ""
            }
          }
        },
        {
          "cardItem": {
            "id": "68616495085350913",
            "type": 2,
            "cover": "https://p16-sign-sg.tiktokcdn.com/aweme/100x100/tos-alisg-avt-0068/smgf5f369c884044a8df770614bbfd64717.jpeg?x-expires=1615294800&x-signature=4jBaVxvskwjaYY7eAVEmrIr9suo%3D",
            "title": "Zach King",
            "subTitle": "@zachking",
            "description": "Bringing a little more wonder into the world, 15 seconds at a time",
            "link": "/@zachking",
            "round": true,
            "playToken": "",
            "keyToken": "",
            "extraInfo": {
              "verified": true,
              "fans": 57500000,
              "likes": "701500000",
              "userId": "68616495085350913",
              "secUid": "MS4wLjABAAAANnzJ9pdfxtlf3m5Ku_M-rCXVitJC13w4GavqyUD3RE8h1cZ-7O9FT-uQ9rCJjU_E",
              "relation": -1,
              "roomId": ""
            }
          }
        },
        {
          "cardItem": {
            "id": "6832705390443365381",
            "type": 2,
            "cover": "https://p16-sign-va.tiktokcdn.com/tos-maliva-avt-0068/3d89056da9f80499eef58f5e006055ed~c5_100x100.jpeg?x-expires=1615294800&x-signature=KEX4Fx0zH5jBQEk8uMhlZ6CuKp0%3D",
            "title": "Chupapi Muñañyo ✨",
            "subTitle": "@jaykindafunny8",
            "description": "CEO of Muñañyoooo\nMuñañitos Click Here!↙️",
            "link": "/@jaykindafunny8",
            "round": true,
            "playToken": "",
            "keyToken": "",
            "extraInfo": {
              "verified": false,
              "fans": 12800000,
              "likes": "229000000",
              "userId": "6832705390443365381",
              "secUid": "MS4wLjABAAAAGOZ3JVuISjArxjkItNPW5B2K9y1hlIsxUssOGzn_aEnSKidP7BB3z_aU00w_Kfpj",
              "relation": -1,
              "roomId": ""
            }
          }
        },
        {
          "cardItem": {
            "id": "6760334624821707782",
            "type": 2,
            "cover": "https://p16-sign-va.tiktokcdn.com/musically-maliva-obj/1661933121226758~c5_100x100.jpeg?x-expires=1615294800&x-signature=q7l0EIyKqJsLdGK2JHI2AIi1VFs%3D",
            "title": "Noah Schnapp",
            "subTitle": "@noahschnapp",
            "description": "downloaded as a joke now i’m addicted\n\ninstagram: noahschnapp",
            "link": "/@noahschnapp",
            "round": true,
            "playToken": "",
            "keyToken": "",
            "extraInfo": {
              "verified": true,
              "fans": 16400000,
              "likes": "252900000",
              "userId": "6760334624821707782",
              "secUid": "MS4wLjABAAAAeinbqYS4L9MRK6jc5ZkDrQXci3rxQdnkyJxQijPPzsPzM7xPVWSUBgTiuqX3y0qk",
              "relation": -1,
              "roomId": ""
            }
          }
        },
        {
          "cardItem": {
            "id": "79609045006872576",
            "type": 2,
            "cover": "https://p16-sign-va.tiktokcdn.com/tos-maliva-avt-0068/daa05c044985f29f552abae49ae4183e~c5_100x100.jpeg?x-expires=1615294800&x-signature=YdGPZc1OgNQftcP1hLIJ%2FOUDrfQ%3D",
            "title": "avani",
            "subTitle": "@avani",
            "description": "if you don’t love me i love you\nMERCH👇🏽",
            "link": "/@avani",
            "round": true,
            "playToken": "",
            "keyToken": "",
            "extraInfo": {
              "verified": true,
              "fans": 31800000,
              "likes": "2200000000",
              "userId": "79609045006872576",
              "secUid": "MS4wLjABAAAAkhSlDFx4BF7OTGSNlbVhAzr-ZvKxbZYDfL_TbRBWoePusRzLqtOA3q6iHp3pd-9R",
              "relation": -1,
              "roomId": ""
            }
          }
        },
        {
          "cardItem": {
            "id": "6767527973299536901",
            "type": 2,
            "cover": "https://p16-sign-va.tiktokcdn.com/tos-maliva-avt-0068/41e1abb4ce1dba723183f74a56b657b5~c5_100x100.jpeg?x-expires=1615294800&x-signature=LyF9hmPLp9%2FBdUg5Ajcc0gJd12E%3D",
            "title": "AbbieHerbert",
            "subTitle": "@abbieherbert_",
            "description": "Model, Wife, Soon to be Milf\nThe Herbert’s YouTube ⬇️\nAbbie@talentxent.com",
            "link": "/@abbieherbert_",
            "round": true,
            "playToken": "",
            "keyToken": "",
            "extraInfo": {
              "verified": true,
              "fans": 6700000,
              "likes": "451600000",
              "userId": "6767527973299536901",
              "secUid": "MS4wLjABAAAAmyJNDiXiVG7rb2M4WVMvjDwJU_Tfw22k8oRPhLxeXbQEmiZ6o1PI8CnULIDk9dah",
              "relation": -1,
              "roomId": ""
            }
          }
        },
        {
          "cardItem": {
            "id": "190068318278651904",
            "type": 2,
            "cover": "https://p16-sign-va.tiktokcdn.com/tos-maliva-avt-0068/8c933ab080d3a54166416afaa3c19cc3~c5_100x100.jpeg?x-expires=1615294800&x-signature=Tgp8e1MfYtE5f7AE6KGpMhfJcb4%3D",
            "title": "James Charles",
            "subTitle": "@jamescharles",
            "description": "Blend, but don’t blend in. 🎨💞\nInsta/YouTube: JamesCharles\nSnap: JamesCharless",
            "link": "/@jamescharles",
            "round": true,
            "playToken": "",
            "keyToken": "",
            "extraInfo": {
              "verified": true,
              "fans": 35600000,
              "likes": "865000000",
              "userId": "190068318278651904",
              "secUid": "MS4wLjABAAAAJHkYGGHc8mp7dytezeOr6IKEGQifLPDBLpVIDSwYUrZHkRBY_rlopvqUtlEjDOEv",
              "relation": -1,
              "roomId": ""
            }
          }
        },
        {
          "cardItem": {
            "id": "6767621542903940102",
            "type": 2,
            "cover": "https://p16-sign-va.tiktokcdn.com/musically-maliva-obj/ae34b3144f24dd17f3810e2c04e41efd~c5_100x100.jpeg?x-expires=1615294800&x-signature=F6TY%2Fz5ljswCuRtHmrQV1Ww3un4%3D",
            "title": "Foodies",
            "subTitle": "@foodies",
            "description": "FOODIES NATION\nBiz - contact@ifoodies.co\nMY LINKS ⬇️",
            "link": "/@foodies",
            "round": true,
            "playToken": "",
            "keyToken": "",
            "extraInfo": {
              "verified": true,
              "fans": 19600000,
              "likes": "955500000",
              "userId": "6767621542903940102",
              "secUid": "MS4wLjABAAAATgYdLA-PXFk2Qhhj7M0RHp84HIpPU-7FHMn5fUXpg5HyYT0LzB0nIj4Ep2Rz6Wp5",
              "relation": -1,
              "roomId": ""
            }
          }
        },
        {
          "cardItem": {
            "id": "6663294979903422470",
            "type": 2,
            "cover": "https://p16-sign-va.tiktokcdn.com/musically-maliva-obj/1627299377282054~c5_100x100.jpeg?x-expires=1615294800&x-signature=8Nr%2Ba1L7nzGZ3hnAOTpnDup%2FfvI%3D",
            "title": "ESPN",
            "subTitle": "@espn",
            "description": "🔥 Click the Instagram logo above and follow us 🔥",
            "link": "/@espn",
            "round": true,
            "playToken": "",
            "keyToken": "",
            "extraInfo": {
              "verified": true,
              "fans": 14000000,
              "likes": "852500000",
              "userId": "6663294979903422470",
              "secUid": "MS4wLjABAAAAbq-1Yqpp1a6u5KbV_sMg93_FK7AN3d6MJeZ3H0Yj3vZXOtqFXXjc2TIkMW7flCxX",
              "relation": -1,
              "roomId": ""
            }
          }
        },
        {
          "cardItem": {
            "id": "6658113054100652038",
            "type": 2,
            "cover": "https://p16-sign-va.tiktokcdn.com/musically-maliva-obj/1663367077635077~c5_100x100.jpeg?x-expires=1615294800&x-signature=l0y0TKz8eorIDxug5cJd%2B4DrsUg%3D",
            "title": "Georgie Boy",
            "subTitle": "@heresyourmonkeycontent",
            "description": "👆YOUTUBE AND INSTA\nheresyourmonkeycontent@yahoo.com\nTap below for Links! 👇",
            "link": "/@heresyourmonkeycontent",
            "round": true,
            "playToken": "",
            "keyToken": "",
            "extraInfo": {
              "verified": false,
              "fans": 13700000,
              "likes": "151400000",
              "userId": "6658113054100652038",
              "secUid": "MS4wLjABAAAA7CyNvLiT5-wfMyn7_KhW2jJM-QZZMgvDH9UjKnlgd2pCWpyI0PUewJn-f_hLOuMD",
              "relation": -1,
              "roomId": ""
            }
          }
        },
        {
          "cardItem": {
            "id": "21609287",
            "type": 2,
            "cover": "https://p16-sign-va.tiktokcdn.com/musically-maliva-obj/1656115901452294~c5_100x100.jpeg?x-expires=1615294800&x-signature=2THlut51gDJyBQXgEQiIMtdgJbM%3D",
            "title": "Jason Derulo",
            "subTitle": "@jasonderulo",
            "description": "“Lifestyle” OUT NOW\nBooking Frank@23-management.com\nFans text 9547585312",
            "link": "/@jasonderulo",
            "round": true,
            "playToken": "",
            "keyToken": "",
            "extraInfo": {
              "verified": true,
              "fans": 43600000,
              "likes": "995900000",
              "userId": "21609287",
              "secUid": "MS4wLjABAAAAC5mIlEsDQSlfaWV6PSINVnfJOJz-eGhbAffi9TDrURw",
              "relation": -1,
              "roomId": ""
            }
          }
        },
        {
          "cardItem": {
            "id": "6727327145951183878",
            "type": 2,
            "cover": "https://p16-sign-va.tiktokcdn.com/musically-maliva-obj/1646315618666501~c5_100x100.jpeg?x-expires=1615294800&x-signature=saOQ%2BqufEDf1xHfcQaSP2m4WnJg%3D",
            "title": "Will Smith",
            "subTitle": "@willsmith",
            "description": "Same kid from West Philly.",
            "link": "/@willsmith",
            "round": true,
            "playToken": "",
            "keyToken": "",
            "extraInfo": {
              "verified": true,
              "fans": 48900000,
              "likes": "282300000",
              "userId": "6727327145951183878",
              "secUid": "MS4wLjABAAAA8ezUaW4ecJX222ObGXxt07F9BIh4QH3-g1P1DHyChT2LLi2cn-vAE2R53-H672ZO",
              "relation": -1,
              "roomId": ""
            }
          }
        },
        {
          "cardItem": {
            "id": "6565170509783334918",
            "type": 2,
            "cover": "https://p16-sign-va.tiktokcdn.com/musically-maliva-obj/1660657719928837~c5_100x100.jpeg?x-expires=1615294800&x-signature=qtm7mOYX2MKHzbPGJdYr7VkI8B8%3D",
            "title": "trishapaytas ",
            "subTitle": "@trishlikefish88",
            "description": "She/Her They/Them🌈Instagram @TrishaPaytasBACKUP🤡 my article for ny mag vulture",
            "link": "/@trishlikefish88",
            "round": true,
            "playToken": "",
            "keyToken": "",
            "extraInfo": {
              "verified": true,
              "fans": 5000000,
              "likes": "301300000",
              "userId": "6565170509783334918",
              "secUid": "MS4wLjABAAAA73uGt8j9y-NUpymMS_kmS3jdQXmLnflKCMkxbxSxyEOTrZYSmNNr22mX6vuBJ6lZ",
              "relation": -1,
              "roomId": ""
            }
          }
        },
        {
          "cardItem": {
            "id": "6738011194222920709",
            "type": 2,
            "cover": "https://p16-sign-va.tiktokcdn.com/tos-maliva-avt-0068/561e2eff2cc34df60b4dea972743d4b2~c5_100x100.jpeg?x-expires=1615294800&x-signature=XrnevPAia1iWB7fA46mw1HAIWkU%3D",
            "title": "Presley",
            "subTitle": "@morganpresleyxo",
            "description": "📩2423 S. Orange Ave. #323 Orlando, FL 32806\n\nsmithmorgan1887@gmail.com\nYT🎥⬇️",
            "link": "/@morganpresleyxo",
            "round": true,
            "playToken": "",
            "keyToken": "",
            "extraInfo": {
              "verified": false,
              "fans": 2400000,
              "likes": "90800000",
              "userId": "6738011194222920709",
              "secUid": "MS4wLjABAAAAi8LARyQq9HYIAU-VOt62Yh9Yu1-mnVqdPZ49kYFVeHIutGGys7gZe9FeB03qXK-d",
              "relation": -1,
              "roomId": ""
            }
          }
        },
        {
          "cardItem": {
            "id": "11956846",
            "type": 2,
            "cover": "https://p16-sign-va.tiktokcdn.com/tos-maliva-avt-0068/16ff8eb79e68675dfee9636ee8f518b4~c5_100x100.jpeg?x-expires=1615294800&x-signature=H311QBiP4aND5ENYUxHZ3Sd2NDQ%3D",
            "title": "The Mannii Show",
            "subTitle": "@the_mannii",
            "description": "🦾👁👄👁🤳🏻 \nʕ•̫͡•ʔ🙏🏼Follow my iNstaGram⤴️ʕ•̫͡•ʔ\nBiZ📧:manniijesus@gmail.com",
            "link": "/@the_mannii",
            "round": true,
            "playToken": "",
            "keyToken": "",
            "extraInfo": {
              "verified": true,
              "fans": 5300000,
              "likes": "195800000",
              "userId": "11956846",
              "secUid": "MS4wLjABAAAAy1sLg0iv55vYPdxhpxUccI_6npLY7pwF6-WPcmYG0Ps",
              "relation": -1,
              "roomId": ""
            }
          }
        },
        {
          "cardItem": {
            "id": "6567760124612624390",
            "type": 2,
            "cover": "https://p16-sign-va.tiktokcdn.com/musically-maliva-obj/1655768604864517~c5_100x100.jpeg?x-expires=1615294800&x-signature=qRn0%2Bkql39YhYkC0qZpQKJAxoX0%3D",
            "title": "Joe",
            "subTitle": "@joealbanese",
            "description": "Subscribe to my channel! :) ❤️⬆️\nRoblox MM2 ft little sister!! 🤣⬇️",
            "link": "/@joealbanese",
            "round": true,
            "playToken": "",
            "keyToken": "",
            "extraInfo": {
              "verified": true,
              "fans": 28700000,
              "likes": "1100000000",
              "userId": "6567760124612624390",
              "secUid": "MS4wLjABAAAAMTpWIYlhG19o74d4lxlaFMEhQTYaSsmaU3vAI97wsr1mm4XojXreNNI-Qsf8P41o",
              "relation": -1,
              "roomId": ""
            }
          }
        }
      ],
      "pageState": {
        "regionAppId": 1233,
        "os": "mac",
        "region": "US",
        "baseURL": "www.tiktok.com",
        "appType": "t",
        "fullUrl": "https://t.tiktok.com/node/share/discover"
      }
    },
    {
      "exploreList": [
        {
          "cardItem": {
            "id": "1607841952743426",
            "type": 3,
            "cover": "https://p16-amd-va.tiktokcdn.com/obj/musically-maliva-obj/4741f83fc0b36ba395bae40b4caaf4de",
            "title": "#foodontiktok",
            "subTitle": "223.5M views",
            "description": "We're here for all the #FoodOnTikTok.",
            "link": "/tag/foodontiktok",
            "round": false,
            "playToken": "",
            "keyToken": "",
            "extraInfo": {
              "views": "223500000",
              "challengeId": "1607841952743426",
              "challengeName": "foodontiktok"
            }
          },
          "videoList": []
        },
        {
          "cardItem": {
            "id": "1635887",
            "type": 3,
            "cover": "https://p16-amd-va.tiktokcdn.com/obj/musically-maliva-obj/9d77b8a5c9afcf8eff2a5648511206d0",
            "title": "#ontherunway",
            "subTitle": "2.3B views",
            "description": "Whether you're hitting your poses for Fashion Month, or just strutting at home, show us what happens when you're #OnTheRunway.",
            "link": "/tag/ontherunway",
            "round": false,
            "playToken": "",
            "keyToken": "",
            "extraInfo": {
              "views": "2300000000",
              "challengeId": "1635887",
              "challengeName": "ontherunway"
            }
          },
          "videoList": []
        },
        {
          "cardItem": {
            "id": "41860",
            "type": 3,
            "cover": "https://p16-amd-va.tiktokcdn.com/obj/musically-maliva-obj/ebecfea584fe94b5f95e6d455b8a15b7",
            "title": "#dayandnight",
            "subTitle": "353.4M views",
            "description": "Turn off the lights and send us a message.",
            "link": "/tag/dayandnight",
            "round": false,
            "playToken": "",
            "keyToken": "",
            "extraInfo": {
              "views": "353400000",
              "challengeId": "41860",
              "challengeName": "dayandnight"
            }
          },
          "videoList": []
        },
        {
          "cardItem": {
            "id": "5841",
            "type": 3,
            "cover": "https://p16-amd-va.tiktokcdn.com/obj/musically-maliva-obj/012b33aa43bc023c5edefe8c6c4cdba6",
            "title": "#Lifestyle",
            "subTitle": "7B views",
            "description": "Whether you're all about wellness or just living your best life, how are you living your dream #Lifestyle?",
            "link": "/tag/Lifestyle",
            "round": false,
            "playToken": "",
            "keyToken": "",
            "extraInfo": {
              "views": "7000000000",
              "challengeId": "5841",
              "challengeName": "Lifestyle"
            }
          },
          "videoList": []
        },
        {
          "cardItem": {
            "id": "1691554469828610",
            "type": 3,
            "cover": "https://p16-sg.tiktokcdn.com/obj/tiktok-obj/09fffb574c37ecc2cc397f4095ccd271",
            "title": "#tiktokwildlifeday",
            "subTitle": "1B views",
            "description": "TikTok is celebrating World Wildlife Day 2021 with the United Nations Environment Programme, creators and other organizations.\n\nShare your support for wildlife protection, or use the official sticker to discover your &quot;wild animal match&quot; 🐘🦁️🦢🦏\n\nDon't forget to tune into the online safaris on TikTok LIVE, where we will be taking you on special tours of four South African Reserves.",
            "link": "/tag/tiktokwildlifeday",
            "round": false,
            "playToken": "",
            "keyToken": "",
            "extraInfo": {
              "views": "1000000000",
              "challengeId": "1691554469828610",
              "challengeName": "tiktokwildlifeday"
            }
          },
          "videoList": []
        },
        {
          "cardItem": {
            "id": "1623823712105477",
            "type": 3,
            "cover": "https://p16-amd-va.tiktokcdn.com/obj/musically-maliva-obj/5ac2885c7d06b8b3c330bf443f15e5a0",
            "title": "#thriftflip",
            "subTitle": "1B views",
            "description": "Whether you love second-hand shops or searching online, show us your best #ThriftFlip.",
            "link": "/tag/thriftflip",
            "round": false,
            "playToken": "",
            "keyToken": "",
            "extraInfo": {
              "views": "1000000000",
              "challengeId": "1623823712105477",
              "challengeName": "thriftflip"
            }
          },
          "videoList": []
        },
        {
          "cardItem": {
            "id": "9979233",
            "type": 3,
            "cover": "https://p16-amd-va.tiktokcdn.com/obj/musically-maliva-obj/585ffc9c5a7f59561b12c7140ed09e76",
            "title": "#science101",
            "subTitle": "220.2M views",
            "description": "Science can be hard, but it doesn't need to be. Make science easy with #Science101.",
            "link": "/tag/science101",
            "round": false,
            "playToken": "",
            "keyToken": "",
            "extraInfo": {
              "views": "220200000",
              "challengeId": "9979233",
              "challengeName": "science101"
            }
          },
          "videoList": []
        },
        {
          "cardItem": {
            "id": "1692516867215366",
            "type": 3,
            "cover": "https://p16-amd-va.tiktokcdn.com/obj/musically-maliva-obj/e4a2139459a1a44f3e878b8951fa5f0a",
            "title": "#whenwomenwin",
            "subTitle": "242.4M views",
            "description": "From change-makers to innovators, here's to the power and strength of women leading movements towards progress across the world. We all win #WhenWomenWin.",
            "link": "/tag/whenwomenwin",
            "round": false,
            "playToken": "",
            "keyToken": "",
            "extraInfo": {
              "views": "242400000",
              "challengeId": "1692516867215366",
              "challengeName": "whenwomenwin"
            }
          },
          "videoList": []
        },
        {
          "cardItem": {
            "id": "23903531",
            "type": 3,
            "cover": "https://p16-amd-va.tiktokcdn.com/obj/musically-maliva-obj/798dbc4e2da3cfe09ec79632a3d72a4c",
            "title": "#glasspainting",
            "subTitle": "610.4M views",
            "description": "Calling all artists! Show us your #GlassPainting.",
            "link": "/tag/glasspainting",
            "round": false,
            "playToken": "",
            "keyToken": "",
            "extraInfo": {
              "views": "610400000",
              "challengeId": "23903531",
              "challengeName": "glasspainting"
            }
          },
          "videoList": []
        },
        {
          "cardItem": {
            "id": "60336197",
            "type": 3,
            "cover": "https://p16-amd-va.tiktokcdn.com/obj/musically-maliva-obj/ce9ace3b9617d127c3532861de9318f5",
            "title": "#seitan",
            "subTitle": "266.7M views",
            "description": "All you need is flour and water, so get cooking with #Seitan.",
            "link": "/tag/seitan",
            "round": false,
            "playToken": "",
            "keyToken": "",
            "extraInfo": {
              "views": "266700000",
              "challengeId": "60336197",
              "challengeName": "seitan"
            }
          },
          "videoList": []
        }
      ],
      "pageState": {
        "regionAppId": 1233,
        "os": "mac",
        "region": "US",
        "baseURL": "www.tiktok.com",
        "appType": "t",
        "fullUrl": "https://t.tiktok.com/node/share/discover"
      }
    },
    {
      "exploreList": [
        {
          "cardItem": {
            "id": "6808287098886424577",
            "type": 1,
            "cover": "https://p16-sg.tiktokcdn.com/aweme/100x100/tos-alisg-i-0000/abb04f991047411f818c8971c9ab2f89.jpeg",
            "title": "Then Leave (feat. Queendom Come)",
            "subTitle": "1.3M videos",
            "description": "BeatKing",
            "link": "/music/Then-Leave-feat-Queendom-Come-6808287098886424577",
            "round": false,
            "playToken": "",
            "keyToken": "",
            "extraInfo": {
              "musicId": "6808287098886424577",
              "playUrl": [
                "https://sf16-ies-music-sg.tiktokcdn.com/obj/tiktok-obj/faac6d7869ea59561bfc2227d88110e6.mp3"
              ],
              "posts": 1300000
            }
          },
          "videoList": []
        },
        {
          "cardItem": {
            "id": "6812545347835922434",
            "type": 1,
            "cover": "https://p16-sg.tiktokcdn.com/aweme/100x100/tos-alisg-i-0000/8dafbb75373a44069c5da80c97f9e8fd.jpeg",
            "title": "Hood Baby",
            "subTitle": "3.3M videos",
            "description": "Kbfr",
            "link": "/music/Hood-Baby-6812545347835922434",
            "round": false,
            "playToken": "",
            "keyToken": "",
            "extraInfo": {
              "musicId": "6812545347835922434",
              "playUrl": [
                "https://sf16-ies-music-sg.tiktokcdn.com/obj/tiktok-obj/14c23eca4f4671136c5c7a38a66f9e05.m4a"
              ],
              "posts": 3300000
            }
          },
          "videoList": []
        },
        {
          "cardItem": {
            "id": "6807966889273346822",
            "type": 1,
            "cover": "https://p16-sg.tiktokcdn.com/aweme/100x100/tos-alisg-i-0000/1bc9ccdb71024095b7ef22a9271cf1e7.jpeg",
            "title": "Dream Girl",
            "subTitle": "14.8M videos",
            "description": "Ir Sais",
            "link": "/music/Dream-Girl-6807966889273346822",
            "round": false,
            "playToken": "",
            "keyToken": "",
            "extraInfo": {
              "musicId": "6807966889273346822",
              "playUrl": [
                "https://sf16-ies-music-sg.tiktokcdn.com/obj/tiktok-obj/387d7b4519e3eb6af28a07160fa5f75f.mp3"
              ],
              "posts": 14800000
            }
          },
          "videoList": []
        },
        {
          "cardItem": {
            "id": "6813134956269947654",
            "type": 1,
            "cover": "https://p16-sg.tiktokcdn.com/aweme/100x100/tos-alisg-i-0000/28de4c2ed0ee47f98dcc0a7ab1f2697e.jpeg",
            "title": "Stunnin' (feat. Harm Franklin)",
            "subTitle": "1.2M videos",
            "description": "Curtis Waters",
            "link": "/music/Stunnin-feat-Harm-Franklin-6813134956269947654",
            "round": false,
            "playToken": "",
            "keyToken": "",
            "extraInfo": {
              "musicId": "6813134956269947654",
              "playUrl": [
                "https://sf16-ies-music-sg.tiktokcdn.com/obj/tiktok-obj/e5c710f2ab8f98c58b5465cf4afb84a9.mp3"
              ],
              "posts": 1200000
            }
          },
          "videoList": []
        },
        {
          "cardItem": {
            "id": "6827517892439968517",
            "type": 1,
            "cover": "https://p16-sg.tiktokcdn.com/aweme/100x100/tos-alisg-i-0000/e348165cfce040039fe9ee63fb2e7ae0.jpeg",
            "title": "Do It",
            "subTitle": "495.7K videos",
            "description": "Chloe x Halle",
            "link": "/music/Do-It-6827517892439968517",
            "round": false,
            "playToken": "",
            "keyToken": "",
            "extraInfo": {
              "musicId": "6827517892439968517",
              "playUrl": [
                "https://sf16-ies-music-sg.tiktokcdn.com/obj/tiktok-obj/22edbf1cc1a90a50152172c36f729e8f.mp3"
              ],
              "posts": 495700
            }
          },
          "videoList": []
        },
        {
          "cardItem": {
            "id": "6834110584288447237",
            "type": 1,
            "cover": "https://p16-sg.tiktokcdn.com/aweme/100x100/tos-alisg-i-0000/7503f7a92b0049d48a80fdffbea51f40.jpeg",
            "title": "Savage Love (Laxed - Siren Beat)",
            "subTitle": "880.9K videos",
            "description": "Jawsh 685 & Jason Derulo",
            "link": "/music/Savage-Love-Laxed-Siren-Beat-6834110584288447237",
            "round": false,
            "playToken": "",
            "keyToken": "",
            "extraInfo": {
              "musicId": "6834110584288447237",
              "playUrl": [
                "https://sf16-ies-music-sg.tiktokcdn.com/obj/tiktok-obj/55660f79de9e40bc8356df5d9ece9b2d.mp3"
              ],
              "posts": 880900
            }
          },
          "videoList": []
        },
        {
          "cardItem": {
            "id": "6754420279457565445",
            "type": 1,
            "cover": "https://p16-sg.tiktokcdn.com/aweme/100x100/tos-alisg-i-0000/a8daea644fa540ff8a8c3025834f8c31.jpeg",
            "title": "Mr. Blue Sky",
            "subTitle": "580.4K videos",
            "description": "Electric Light Orchestra",
            "link": "/music/Mr-Blue-Sky-6754420279457565445",
            "round": false,
            "playToken": "",
            "keyToken": "",
            "extraInfo": {
              "musicId": "6754420279457565445",
              "playUrl": [
                "https://sf16-ies-music-sg.tiktokcdn.com/obj/tiktok-obj/72bc6715e0b6726f3806f1bce1b0630f.mp3"
              ],
              "posts": 580400
            }
          },
          "videoList": []
        },
        {
          "cardItem": {
            "id": "6746993352891189249",
            "type": 1,
            "cover": "https://p16-sg.tiktokcdn.com/aweme/100x100/tos-alisg-i-0000/35eb9d866b2c47d4811132f3c3fa904c.jpeg",
            "title": "Monkeys Spinning Monkeys",
            "subTitle": "5.9M videos",
            "description": "Kevin MacLeod",
            "link": "/music/Monkeys-Spinning-Monkeys-6746993352891189249",
            "round": false,
            "playToken": "",
            "keyToken": "",
            "extraInfo": {
              "musicId": "6746993352891189249",
              "playUrl": [
                "https://sf16-ies-music-sg.tiktokcdn.com/obj/tiktok-obj/a7c68545b238686d79179e25ee990183.m4a"
              ],
              "posts": 5900000
            }
          },
          "videoList": []
        },
        {
          "cardItem": {
            "id": "6691366574592396038",
            "type": 1,
            "cover": "https://p16-sg.tiktokcdn.com/aweme/100x100/tos-alisg-v-2102/66136bd201e44750a35867f8e4727c4d.jpeg",
            "title": "Woah (feat. D3Mstreet)",
            "subTitle": "12.6M videos",
            "description": "KRYPTO9095",
            "link": "/music/Woah-feat-D3Mstreet-6691366574592396038",
            "round": false,
            "playToken": "",
            "keyToken": "",
            "extraInfo": {
              "musicId": "6691366574592396038",
              "playUrl": [
                "https://sf16-ies-music-sg.tiktokcdn.com/obj/tiktok-obj/1daadedc15bd3aa203a4620bac0e1f94.mp3"
              ],
              "posts": 12600000
            }
          },
          "videoList": []
        }
      ],
      "pageState": {
        "regionAppId": 1233,
        "os": "mac",
        "region": "US",
        "baseURL": "www.tiktok.com",
        "appType": "t",
        "fullUrl": "https://t.tiktok.com/node/share/discover"
      }
    }
  ],
  "statusCode": 0,
  "errMsg": null
}
